{
  "artists": {
    "title": "Artistas (Por Scrobbles)",
    "data": {
      "JPEGMAFIA": 1250,
      "Death Grips": 924,
      "Héctor Lavoe": 746,
      "Bad Bunny": 592,
      "Dillom": 549,
      "ataquemos": 543,
      "Guerreros Del Bajo": 541,
      "Quadeca": 510,
      "Pink Floyd": 483,
      "Injury Reserve": 468,
      "C.R.O": 432,
      "Gonzalo Genek": 402,
      "Murder": 397,
      "A$AP Rocky": 389,
      "Summer 2000": 387
    },
    "total": 8613,
    "details": {
      "JPEGMAFIA": {
        "user_count": 2,
        "total_scrobbles": 1250,
        "shared_users": [
          "EliasJ72",
          "Rocky_stereo"
        ],
        "user_plays": {},
        "artist": "",
        "album": "",
        "track": ""
      },
      "Death Grips": {
        "user_count": 1,
        "total_scrobbles": 924,
        "shared_users": [
          "EliasJ72"
        ],
        "user_plays": {},
        "artist": "",
        "album": "",
        "track": ""
      },
      "Héctor Lavoe": {
        "user_count": 1,
        "total_scrobbles": 746,
        "shared_users": [
          "Rocky_stereo"
        ],
        "user_plays": {},
        "artist": "",
        "album": "",
        "track": ""
      },
      "Bad Bunny": {
        "user_count": 2,
        "total_scrobbles": 592,
        "shared_users": [
          "EliasJ72",
          "Rocky_stereo"
        ],
        "user_plays": {},
        "artist": "",
        "album": "",
        "track": ""
      },
      "Dillom": {
        "user_count": 2,
        "total_scrobbles": 549,
        "shared_users": [
          "EliasJ72",
          "Rocky_stereo"
        ],
        "user_plays": {},
        "artist": "",
        "album": "",
        "track": ""
      },
      "ataquemos": {
        "user_count": 1,
        "total_scrobbles": 543,
        "shared_users": [
          "Rocky_stereo"
        ],
        "user_plays": {},
        "artist": "",
        "album": "",
        "track": ""
      },
      "Guerreros Del Bajo": {
        "user_count": 2,
        "total_scrobbles": 541,
        "shared_users": [
          "EliasJ72",
          "Rocky_stereo"
        ],
        "user_plays": {},
        "artist": "",
        "album": "",
        "track": ""
      },
      "Quadeca": {
        "user_count": 1,
        "total_scrobbles": 510,
        "shared_users": [
          "EliasJ72"
        ],
        "user_plays": {},
        "artist": "",
        "album": "",
        "track": ""
      },
      "Pink Floyd": {
        "user_count": 2,
        "total_scrobbles": 483,
        "shared_users": [
          "EliasJ72",
          "Rocky_stereo"
        ],
        "user_plays": {},
        "artist": "",
        "album": "",
        "track": ""
      },
      "Injury Reserve": {
        "user_count": 1,
        "total_scrobbles": 468,
        "shared_users": [
          "EliasJ72"
        ],
        "user_plays": {},
        "artist": "",
        "album": "",
        "track": ""
      },
      "C.R.O": {
        "user_count": 1,
        "total_scrobbles": 432,
        "shared_users": [
          "Rocky_stereo"
        ],
        "user_plays": {},
        "artist": "",
        "album": "",
        "track": ""
      },
      "Gonzalo Genek": {
        "user_count": 1,
        "total_scrobbles": 402,
        "shared_users": [
          "Rocky_stereo"
        ],
        "user_plays": {},
        "artist": "",
        "album": "",
        "track": ""
      },
      "Murder": {
        "user_count": 1,
        "total_scrobbles": 397,
        "shared_users": [
          "Rocky_stereo"
        ],
        "user_plays": {},
        "artist": "",
        "album": "",
        "track": ""
      },
      "A$AP Rocky": {
        "user_count": 2,
        "total_scrobbles": 389,
        "shared_users": [
          "EliasJ72",
          "Rocky_stereo"
        ],
        "user_plays": {},
        "artist": "",
        "album": "",
        "track": ""
      },
      "Summer 2000": {
        "user_count": 1,
        "total_scrobbles": 387,
        "shared_users": [
          "Rocky_stereo"
        ],
        "user_plays": {},
        "artist": "",
        "album": "",
        "track": ""
      }
    },
    "type": "scrobbles"
  },
  "albums": {
    "title": "Álbumes (Por Scrobbles)",
    "data": {
      "Guerreros Del Bajo - Dos Mil Siempre": 431,
      "Dillom - Por cesárea": 384,
      "Injury Reserve - By the Time I Get to Phoenix": 288,
      "JPEGMAFIA - All My Heroes Are Cornballs": 285,
      "Quadeca - Scrapyard": 263,
      "Death Grips - The Money Store": 242,
      "Gonzalo Genek - Licor Amor & Jazz": 237,
      "Hakushi Hasegawa - Mahōgakkō": 235,
      "JPEGMAFIA - I LAY DOWN MY LIFE FOR YOU": 217,
      "Pedro Mo - Ensayos del camarada Lacrasoft y algunos cómplices metafísicos": 216,
      "Radiohead - In Rainbows": 205,
      "Bad Bunny - DeBÍ TiRAR MáS FOToS": 200,
      "Death Grips - The Powers That B": 199,
      "Summer 2000 - Ellie Kemper": 198,
      "Bad Bunny - Un Verano Sin Ti": 174
    },
    "total": 3774,
    "details": {
      "Guerreros Del Bajo - Dos Mil Siempre": {
        "user_count": 2,
        "total_scrobbles": 431,
        "shared_users": [
          "EliasJ72",
          "Rocky_stereo"
        ],
        "user_plays": {},
        "artist": "Guerreros Del Bajo",
        "album": "Dos Mil Siempre",
        "track": ""
      },
      "Dillom - Por cesárea": {
        "user_count": 2,
        "total_scrobbles": 384,
        "shared_users": [
          "EliasJ72",
          "Rocky_stereo"
        ],
        "user_plays": {},
        "artist": "Dillom",
        "album": "Por cesárea",
        "track": ""
      },
      "Injury Reserve - By the Time I Get to Phoenix": {
        "user_count": 1,
        "total_scrobbles": 288,
        "shared_users": [
          "EliasJ72"
        ],
        "user_plays": {},
        "artist": "Injury Reserve",
        "album": "By the Time I Get to Phoenix",
        "track": ""
      },
      "JPEGMAFIA - All My Heroes Are Cornballs": {
        "user_count": 1,
        "total_scrobbles": 285,
        "shared_users": [
          "EliasJ72"
        ],
        "user_plays": {},
        "artist": "JPEGMAFIA",
        "album": "All My Heroes Are Cornballs",
        "track": ""
      },
      "Quadeca - Scrapyard": {
        "user_count": 1,
        "total_scrobbles": 263,
        "shared_users": [
          "EliasJ72"
        ],
        "user_plays": {},
        "artist": "Quadeca",
        "album": "Scrapyard",
        "track": ""
      },
      "Death Grips - The Money Store": {
        "user_count": 1,
        "total_scrobbles": 242,
        "shared_users": [
          "EliasJ72"
        ],
        "user_plays": {},
        "artist": "Death Grips",
        "album": "The Money Store",
        "track": ""
      },
      "Gonzalo Genek - Licor Amor & Jazz": {
        "user_count": 1,
        "total_scrobbles": 237,
        "shared_users": [
          "Rocky_stereo"
        ],
        "user_plays": {},
        "artist": "Gonzalo Genek",
        "album": "Licor Amor & Jazz",
        "track": ""
      },
      "Hakushi Hasegawa - Mahōgakkō": {
        "user_count": 1,
        "total_scrobbles": 235,
        "shared_users": [
          "EliasJ72"
        ],
        "user_plays": {},
        "artist": "Hakushi Hasegawa",
        "album": "Mahōgakkō",
        "track": ""
      },
      "JPEGMAFIA - I LAY DOWN MY LIFE FOR YOU": {
        "user_count": 2,
        "total_scrobbles": 217,
        "shared_users": [
          "EliasJ72",
          "Rocky_stereo"
        ],
        "user_plays": {},
        "artist": "JPEGMAFIA",
        "album": "I LAY DOWN MY LIFE FOR YOU",
        "track": ""
      },
      "Pedro Mo - Ensayos del camarada Lacrasoft y algunos cómplices metafísicos": {
        "user_count": 1,
        "total_scrobbles": 216,
        "shared_users": [
          "Rocky_stereo"
        ],
        "user_plays": {},
        "artist": "Pedro Mo",
        "album": "Ensayos del camarada Lacrasoft y algunos cómplices metafísicos",
        "track": ""
      },
      "Radiohead - In Rainbows": {
        "user_count": 2,
        "total_scrobbles": 205,
        "shared_users": [
          "EliasJ72",
          "Rocky_stereo"
        ],
        "user_plays": {},
        "artist": "Radiohead",
        "album": "In Rainbows",
        "track": ""
      },
      "Bad Bunny - DeBÍ TiRAR MáS FOToS": {
        "user_count": 2,
        "total_scrobbles": 200,
        "shared_users": [
          "EliasJ72",
          "Rocky_stereo"
        ],
        "user_plays": {},
        "artist": "Bad Bunny",
        "album": "DeBÍ TiRAR MáS FOToS",
        "track": ""
      },
      "Death Grips - The Powers That B": {
        "user_count": 1,
        "total_scrobbles": 199,
        "shared_users": [
          "EliasJ72"
        ],
        "user_plays": {},
        "artist": "Death Grips",
        "album": "The Powers That B",
        "track": ""
      },
      "Summer 2000 - Ellie Kemper": {
        "user_count": 1,
        "total_scrobbles": 198,
        "shared_users": [
          "Rocky_stereo"
        ],
        "user_plays": {},
        "artist": "Summer 2000",
        "album": "Ellie Kemper",
        "track": ""
      },
      "Bad Bunny - Un Verano Sin Ti": {
        "user_count": 1,
        "total_scrobbles": 174,
        "shared_users": [
          "Rocky_stereo"
        ],
        "user_plays": {},
        "artist": "Bad Bunny",
        "album": "Un Verano Sin Ti",
        "track": ""
      }
    },
    "type": "scrobbles"
  },
  "tracks": {
    "title": "Canciones (Por Scrobbles)",
    "data": {
      "Daske Gaitán - Me Enamoraste": 89,
      "Sissy Spacek - Untitled": 78,
      "El Dedos - Al Norte De Sus Piernas": 73,
      "Dillom - Buenos tiempos": 72,
      "Ghais Guevara - This Ski Mask Ain't For COVID": 68,
      "Laghonia - My Love": 68,
      "Héctor Lavoe - Un Amor De La Calle": 66,
      "DJ RaMeMes (O DESTRUIDOR DO FUNK) - SENTANDO NA GLOCK RAJADA": 63,
      "Injury Reserve - Superman That": 61,
      "Yan Block - 444": 59,
      "Bardero$ - $$$": 58,
      "Isla Bonita - esperandote": 58,
      "The Smashing Pumpkins - Cupid De Locke - Remastered 2012": 57,
      "Guerreros Del Bajo - Sabanas": 56,
      "Héctor Lavoe - ¿De Qué Tamaño Es Tu Amor?": 55
    },
    "total": 981,
    "details": {
      "Daske Gaitán - Me Enamoraste": {
        "user_count": 1,
        "total_scrobbles": 89,
        "shared_users": [
          "Rocky_stereo"
        ],
        "user_plays": {},
        "artist": "Daske Gaitán",
        "album": "",
        "track": "Me Enamoraste"
      },
      "Sissy Spacek - Untitled": {
        "user_count": 1,
        "total_scrobbles": 78,
        "shared_users": [
          "EliasJ72"
        ],
        "user_plays": {},
        "artist": "Sissy Spacek",
        "album": "",
        "track": "Untitled"
      },
      "El Dedos - Al Norte De Sus Piernas": {
        "user_count": 1,
        "total_scrobbles": 73,
        "shared_users": [
          "Rocky_stereo"
        ],
        "user_plays": {},
        "artist": "El Dedos",
        "album": "",
        "track": "Al Norte De Sus Piernas"
      },
      "Dillom - Buenos tiempos": {
        "user_count": 2,
        "total_scrobbles": 72,
        "shared_users": [
          "EliasJ72",
          "Rocky_stereo"
        ],
        "user_plays": {},
        "artist": "Dillom",
        "album": "",
        "track": "Buenos tiempos"
      },
      "Ghais Guevara - This Ski Mask Ain't For COVID": {
        "user_count": 1,
        "total_scrobbles": 68,
        "shared_users": [
          "EliasJ72"
        ],
        "user_plays": {},
        "artist": "Ghais Guevara",
        "album": "",
        "track": "This Ski Mask Ain't For COVID"
      },
      "Laghonia - My Love": {
        "user_count": 1,
        "total_scrobbles": 68,
        "shared_users": [
          "Rocky_stereo"
        ],
        "user_plays": {},
        "artist": "Laghonia",
        "album": "",
        "track": "My Love"
      },
      "Héctor Lavoe - Un Amor De La Calle": {
        "user_count": 1,
        "total_scrobbles": 66,
        "shared_users": [
          "Rocky_stereo"
        ],
        "user_plays": {},
        "artist": "Héctor Lavoe",
        "album": "",
        "track": "Un Amor De La Calle"
      },
      "DJ RaMeMes (O DESTRUIDOR DO FUNK) - SENTANDO NA GLOCK RAJADA": {
        "user_count": 1,
        "total_scrobbles": 63,
        "shared_users": [
          "EliasJ72"
        ],
        "user_plays": {},
        "artist": "DJ RaMeMes (O DESTRUIDOR DO FUNK)",
        "album": "",
        "track": "SENTANDO NA GLOCK RAJADA"
      },
      "Injury Reserve - Superman That": {
        "user_count": 1,
        "total_scrobbles": 61,
        "shared_users": [
          "EliasJ72"
        ],
        "user_plays": {},
        "artist": "Injury Reserve",
        "album": "",
        "track": "Superman That"
      },
      "Yan Block - 444": {
        "user_count": 1,
        "total_scrobbles": 59,
        "shared_users": [
          "Rocky_stereo"
        ],
        "user_plays": {},
        "artist": "Yan Block",
        "album": "",
        "track": "444"
      },
      "Bardero$ - $$$": {
        "user_count": 1,
        "total_scrobbles": 58,
        "shared_users": [
          "Rocky_stereo"
        ],
        "user_plays": {},
        "artist": "Bardero$",
        "album": "",
        "track": "$$$"
      },
      "Isla Bonita - esperandote": {
        "user_count": 1,
        "total_scrobbles": 58,
        "shared_users": [
          "Rocky_stereo"
        ],
        "user_plays": {},
        "artist": "Isla Bonita",
        "album": "",
        "track": "esperandote"
      },
      "The Smashing Pumpkins - Cupid De Locke - Remastered 2012": {
        "user_count": 1,
        "total_scrobbles": 57,
        "shared_users": [
          "Rocky_stereo"
        ],
        "user_plays": {},
        "artist": "The Smashing Pumpkins",
        "album": "",
        "track": "Cupid De Locke - Remastered 2012"
      },
      "Guerreros Del Bajo - Sabanas": {
        "user_count": 2,
        "total_scrobbles": 56,
        "shared_users": [
          "EliasJ72",
          "Rocky_stereo"
        ],
        "user_plays": {},
        "artist": "Guerreros Del Bajo",
        "album": "",
        "track": "Sabanas"
      },
      "Héctor Lavoe - ¿De Qué Tamaño Es Tu Amor?": {
        "user_count": 1,
        "total_scrobbles": 55,
        "shared_users": [
          "Rocky_stereo"
        ],
        "user_plays": {},
        "artist": "Héctor Lavoe",
        "album": "",
        "track": "¿De Qué Tamaño Es Tu Amor?"
      }
    },
    "type": "scrobbles"
  },
  "genres": {
    "title": "Géneros (Por Scrobbles)",
    "data": {
      "Hip-Hop": 5708,
      "rap": 4837,
      "latin": 3656,
      "electronic": 3060,
      "shoegaze": 2827,
      "experimental": 2736,
      "salsa": 2695,
      "rock": 2655,
      "indie": 2613,
      "hip hop": 2365,
      "experimental hip hop": 2125,
      "alternative": 1891,
      "puerto rico": 1803,
      "dream pop": 1797,
      "argentina": 1658
    },
    "total": 42426,
    "details": {
      "Hip-Hop": {
        "user_count": 2,
        "total_scrobbles": 5708,
        "shared_users": [
          "Rocky_stereo",
          "EliasJ72"
        ],
        "user_plays": {},
        "artist": "",
        "album": "",
        "track": ""
      },
      "rap": {
        "user_count": 2,
        "total_scrobbles": 4837,
        "shared_users": [
          "Rocky_stereo",
          "EliasJ72"
        ],
        "user_plays": {},
        "artist": "",
        "album": "",
        "track": ""
      },
      "latin": {
        "user_count": 2,
        "total_scrobbles": 3656,
        "shared_users": [
          "Rocky_stereo",
          "EliasJ72"
        ],
        "user_plays": {},
        "artist": "",
        "album": "",
        "track": ""
      },
      "electronic": {
        "user_count": 2,
        "total_scrobbles": 3060,
        "shared_users": [
          "Rocky_stereo",
          "EliasJ72"
        ],
        "user_plays": {},
        "artist": "",
        "album": "",
        "track": ""
      },
      "shoegaze": {
        "user_count": 2,
        "total_scrobbles": 2827,
        "shared_users": [
          "Rocky_stereo",
          "EliasJ72"
        ],
        "user_plays": {},
        "artist": "",
        "album": "",
        "track": ""
      },
      "experimental": {
        "user_count": 2,
        "total_scrobbles": 2736,
        "shared_users": [
          "Rocky_stereo",
          "EliasJ72"
        ],
        "user_plays": {},
        "artist": "",
        "album": "",
        "track": ""
      },
      "salsa": {
        "user_count": 2,
        "total_scrobbles": 2695,
        "shared_users": [
          "Rocky_stereo",
          "EliasJ72"
        ],
        "user_plays": {},
        "artist": "",
        "album": "",
        "track": ""
      },
      "rock": {
        "user_count": 2,
        "total_scrobbles": 2655,
        "shared_users": [
          "Rocky_stereo",
          "EliasJ72"
        ],
        "user_plays": {},
        "artist": "",
        "album": "",
        "track": ""
      },
      "indie": {
        "user_count": 2,
        "total_scrobbles": 2613,
        "shared_users": [
          "Rocky_stereo",
          "EliasJ72"
        ],
        "user_plays": {},
        "artist": "",
        "album": "",
        "track": ""
      },
      "hip hop": {
        "user_count": 2,
        "total_scrobbles": 2365,
        "shared_users": [
          "Rocky_stereo",
          "EliasJ72"
        ],
        "user_plays": {},
        "artist": "",
        "album": "",
        "track": ""
      },
      "experimental hip hop": {
        "user_count": 2,
        "total_scrobbles": 2125,
        "shared_users": [
          "Rocky_stereo",
          "EliasJ72"
        ],
        "user_plays": {},
        "artist": "",
        "album": "",
        "track": ""
      },
      "alternative": {
        "user_count": 2,
        "total_scrobbles": 1891,
        "shared_users": [
          "Rocky_stereo",
          "EliasJ72"
        ],
        "user_plays": {},
        "artist": "",
        "album": "",
        "track": ""
      },
      "puerto rico": {
        "user_count": 2,
        "total_scrobbles": 1803,
        "shared_users": [
          "Rocky_stereo",
          "EliasJ72"
        ],
        "user_plays": {},
        "artist": "",
        "album": "",
        "track": ""
      },
      "dream pop": {
        "user_count": 2,
        "total_scrobbles": 1797,
        "shared_users": [
          "Rocky_stereo",
          "EliasJ72"
        ],
        "user_plays": {},
        "artist": "",
        "album": "",
        "track": ""
      },
      "argentina": {
        "user_count": 2,
        "total_scrobbles": 1658,
        "shared_users": [
          "Rocky_stereo",
          "EliasJ72"
        ],
        "user_plays": {},
        "artist": "",
        "album": "",
        "track": ""
      }
    },
    "type": "scrobbles"
  },
  "labels": {
    "title": "Sellos (Por Scrobbles)",
    "data": {
      "[no label]": 1157,
      "Columbia": 637,
      "Fania": 580,
      "Harvest": 377,
      "RCA": 370,
      "XL Recordings": 317,
      "Epic": 303,
      "EQT Recordings": 288,
      "Atlantic": 288,
      "PEGGY": 286,
      "Rimas": 282,
      "Ninja Tune": 224,
      "c h point records": 198,
      "Lazarus Audio Products": 189,
      "Pink Floyd Records": 188
    },
    "total": 5684,
    "details": {
      "[no label]": {
        "user_count": 2,
        "total_scrobbles": 1157,
        "shared_users": [
          "EliasJ72",
          "Rocky_stereo"
        ],
        "user_plays": {},
        "artist": "",
        "album": "",
        "track": ""
      },
      "Columbia": {
        "user_count": 2,
        "total_scrobbles": 637,
        "shared_users": [
          "EliasJ72",
          "Rocky_stereo"
        ],
        "user_plays": {},
        "artist": "",
        "album": "",
        "track": ""
      },
      "Fania": {
        "user_count": 2,
        "total_scrobbles": 580,
        "shared_users": [
          "EliasJ72",
          "Rocky_stereo"
        ],
        "user_plays": {},
        "artist": "",
        "album": "",
        "track": ""
      },
      "Harvest": {
        "user_count": 2,
        "total_scrobbles": 377,
        "shared_users": [
          "EliasJ72",
          "Rocky_stereo"
        ],
        "user_plays": {},
        "artist": "",
        "album": "",
        "track": ""
      },
      "RCA": {
        "user_count": 2,
        "total_scrobbles": 370,
        "shared_users": [
          "EliasJ72",
          "Rocky_stereo"
        ],
        "user_plays": {},
        "artist": "",
        "album": "",
        "track": ""
      },
      "XL Recordings": {
        "user_count": 2,
        "total_scrobbles": 317,
        "shared_users": [
          "EliasJ72",
          "Rocky_stereo"
        ],
        "user_plays": {},
        "artist": "",
        "album": "",
        "track": ""
      },
      "Epic": {
        "user_count": 2,
        "total_scrobbles": 303,
        "shared_users": [
          "EliasJ72",
          "Rocky_stereo"
        ],
        "user_plays": {},
        "artist": "",
        "album": "",
        "track": ""
      },
      "EQT Recordings": {
        "user_count": 1,
        "total_scrobbles": 288,
        "shared_users": [
          "EliasJ72"
        ],
        "user_plays": {},
        "artist": "",
        "album": "",
        "track": ""
      },
      "Atlantic": {
        "user_count": 2,
        "total_scrobbles": 288,
        "shared_users": [
          "EliasJ72",
          "Rocky_stereo"
        ],
        "user_plays": {},
        "artist": "",
        "album": "",
        "track": ""
      },
      "PEGGY": {
        "user_count": 2,
        "total_scrobbles": 286,
        "shared_users": [
          "EliasJ72",
          "Rocky_stereo"
        ],
        "user_plays": {},
        "artist": "",
        "album": "",
        "track": ""
      },
      "Rimas": {
        "user_count": 2,
        "total_scrobbles": 282,
        "shared_users": [
          "EliasJ72",
          "Rocky_stereo"
        ],
        "user_plays": {},
        "artist": "",
        "album": "",
        "track": ""
      },
      "Ninja Tune": {
        "user_count": 2,
        "total_scrobbles": 224,
        "shared_users": [
          "EliasJ72",
          "Rocky_stereo"
        ],
        "user_plays": {},
        "artist": "",
        "album": "",
        "track": ""
      },
      "c h point records": {
        "user_count": 1,
        "total_scrobbles": 198,
        "shared_users": [
          "Rocky_stereo"
        ],
        "user_plays": {},
        "artist": "",
        "album": "",
        "track": ""
      },
      "Lazarus Audio Products": {
        "user_count": 1,
        "total_scrobbles": 189,
        "shared_users": [
          "Rocky_stereo"
        ],
        "user_plays": {},
        "artist": "",
        "album": "",
        "track": ""
      },
      "Pink Floyd Records": {
        "user_count": 1,
        "total_scrobbles": 188,
        "shared_users": [
          "Rocky_stereo"
        ],
        "user_plays": {},
        "artist": "",
        "album": "",
        "track": ""
      }
    },
    "type": "scrobbles"
  },
  "release_years": {
    "title": "Años de Lanzamiento (Por Scrobbles)",
    "data": {
      "2024": 1561,
      "2025": 1337,
      "2016": 1206,
      "2020": 1171,
      "2023": 1081,
      "2019": 1013,
      "2021": 998,
      "2012": 992,
      "2017": 846,
      "2022": 814,
      "2008": 769,
      "2015": 762,
      "2018": 690,
      "2014": 634,
      "2013": 625
    },
    "total": 14499,
    "details": {
      "2024": {
        "user_count": 2,
        "total_scrobbles": 1561,
        "shared_users": [
          "Rocky_stereo",
          "EliasJ72"
        ],
        "user_plays": {},
        "artist": "",
        "album": "",
        "track": ""
      },
      "2025": {
        "user_count": 2,
        "total_scrobbles": 1337,
        "shared_users": [
          "Rocky_stereo",
          "EliasJ72"
        ],
        "user_plays": {},
        "artist": "",
        "album": "",
        "track": ""
      },
      "2016": {
        "user_count": 2,
        "total_scrobbles": 1206,
        "shared_users": [
          "Rocky_stereo",
          "EliasJ72"
        ],
        "user_plays": {},
        "artist": "",
        "album": "",
        "track": ""
      },
      "2020": {
        "user_count": 2,
        "total_scrobbles": 1171,
        "shared_users": [
          "Rocky_stereo",
          "EliasJ72"
        ],
        "user_plays": {},
        "artist": "",
        "album": "",
        "track": ""
      },
      "2023": {
        "user_count": 2,
        "total_scrobbles": 1081,
        "shared_users": [
          "Rocky_stereo",
          "EliasJ72"
        ],
        "user_plays": {},
        "artist": "",
        "album": "",
        "track": ""
      },
      "2019": {
        "user_count": 2,
        "total_scrobbles": 1013,
        "shared_users": [
          "Rocky_stereo",
          "EliasJ72"
        ],
        "user_plays": {},
        "artist": "",
        "album": "",
        "track": ""
      },
      "2021": {
        "user_count": 2,
        "total_scrobbles": 998,
        "shared_users": [
          "Rocky_stereo",
          "EliasJ72"
        ],
        "user_plays": {},
        "artist": "",
        "album": "",
        "track": ""
      },
      "2012": {
        "user_count": 2,
        "total_scrobbles": 992,
        "shared_users": [
          "Rocky_stereo",
          "EliasJ72"
        ],
        "user_plays": {},
        "artist": "",
        "album": "",
        "track": ""
      },
      "2017": {
        "user_count": 2,
        "total_scrobbles": 846,
        "shared_users": [
          "Rocky_stereo",
          "EliasJ72"
        ],
        "user_plays": {},
        "artist": "",
        "album": "",
        "track": ""
      },
      "2022": {
        "user_count": 2,
        "total_scrobbles": 814,
        "shared_users": [
          "Rocky_stereo",
          "EliasJ72"
        ],
        "user_plays": {},
        "artist": "",
        "album": "",
        "track": ""
      },
      "2008": {
        "user_count": 2,
        "total_scrobbles": 769,
        "shared_users": [
          "Rocky_stereo",
          "EliasJ72"
        ],
        "user_plays": {},
        "artist": "",
        "album": "",
        "track": ""
      },
      "2015": {
        "user_count": 2,
        "total_scrobbles": 762,
        "shared_users": [
          "Rocky_stereo",
          "EliasJ72"
        ],
        "user_plays": {},
        "artist": "",
        "album": "",
        "track": ""
      },
      "2018": {
        "user_count": 2,
        "total_scrobbles": 690,
        "shared_users": [
          "Rocky_stereo",
          "EliasJ72"
        ],
        "user_plays": {},
        "artist": "",
        "album": "",
        "track": ""
      },
      "2014": {
        "user_count": 2,
        "total_scrobbles": 634,
        "shared_users": [
          "Rocky_stereo",
          "EliasJ72"
        ],
        "user_plays": {},
        "artist": "",
        "album": "",
        "track": ""
      },
      "2013": {
        "user_count": 2,
        "total_scrobbles": 625,
        "shared_users": [
          "Rocky_stereo",
          "EliasJ72"
        ],
        "user_plays": {},
        "artist": "",
        "album": "",
        "track": ""
      }
    },
    "type": "scrobbles"
  },
  "all_combined": {
    "title": "Top 15 Global por Scrobbles",
    "data": {
      "Release_years: 2010s": 7888,
      "Release_years: 2020s+": 6962,
      "Genres: Hip-Hop": 5708,
      "Genres: rap": 4837,
      "Genres: latin": 3656,
      "Release_years: 2000s": 3357,
      "Release_years: 1990s": 3096,
      "Genres: electronic": 3060,
      "Genres: shoegaze": 2827,
      "Release_years: 1980s": 1372,
      "Artists: JPEGMAFIA": 1250,
      "Labels: [no label]": 1157,
      "Artists: Death Grips": 924,
      "Artists: Héctor Lavoe": 746,
      "Labels: Columbia": 637
    },
    "total": 47477,
    "details": {
      "Release_years: 2010s": {
        "original_name": "2010s",
        "category": "release_years",
        "user_count": 2,
        "total_scrobbles": 7888,
        "shared_users": [
          "Rocky_stereo",
          "EliasJ72"
        ]
      },
      "Release_years: 2020s+": {
        "original_name": "2020s+",
        "category": "release_years",
        "user_count": 2,
        "total_scrobbles": 6962,
        "shared_users": [
          "Rocky_stereo",
          "EliasJ72"
        ]
      },
      "Genres: Hip-Hop": {
        "original_name": "Hip-Hop",
        "category": "genres",
        "user_count": 2,
        "total_scrobbles": 5708,
        "shared_users": [
          "Rocky_stereo",
          "EliasJ72"
        ]
      },
      "Genres: rap": {
        "original_name": "rap",
        "category": "genres",
        "user_count": 2,
        "total_scrobbles": 4837,
        "shared_users": [
          "Rocky_stereo",
          "EliasJ72"
        ]
      },
      "Genres: latin": {
        "original_name": "latin",
        "category": "genres",
        "user_count": 2,
        "total_scrobbles": 3656,
        "shared_users": [
          "Rocky_stereo",
          "EliasJ72"
        ]
      },
      "Release_years: 2000s": {
        "original_name": "2000s",
        "category": "release_years",
        "user_count": 2,
        "total_scrobbles": 3357,
        "shared_users": [
          "Rocky_stereo",
          "EliasJ72"
        ]
      },
      "Release_years: 1990s": {
        "original_name": "1990s",
        "category": "release_years",
        "user_count": 2,
        "total_scrobbles": 3096,
        "shared_users": [
          "Rocky_stereo",
          "EliasJ72"
        ]
      },
      "Genres: electronic": {
        "original_name": "electronic",
        "category": "genres",
        "user_count": 2,
        "total_scrobbles": 3060,
        "shared_users": [
          "Rocky_stereo",
          "EliasJ72"
        ]
      },
      "Genres: shoegaze": {
        "original_name": "shoegaze",
        "category": "genres",
        "user_count": 2,
        "total_scrobbles": 2827,
        "shared_users": [
          "Rocky_stereo",
          "EliasJ72"
        ]
      },
      "Release_years: 1980s": {
        "original_name": "1980s",
        "category": "release_years",
        "user_count": 2,
        "total_scrobbles": 1372,
        "shared_users": [
          "Rocky_stereo",
          "EliasJ72"
        ]
      },
      "Artists: JPEGMAFIA": {
        "original_name": "JPEGMAFIA",
        "category": "artists",
        "user_count": 2,
        "total_scrobbles": 1250,
        "shared_users": [
          "EliasJ72",
          "Rocky_stereo"
        ]
      },
      "Labels: [no label]": {
        "original_name": "[no label]",
        "category": "labels",
        "user_count": 2,
        "total_scrobbles": 1157,
        "shared_users": [
          "EliasJ72",
          "Rocky_stereo"
        ]
      },
      "Artists: Death Grips": {
        "original_name": "Death Grips",
        "category": "artists",
        "user_count": 1,
        "total_scrobbles": 924,
        "shared_users": [
          "EliasJ72"
        ]
      },
      "Artists: Héctor Lavoe": {
        "original_name": "Héctor Lavoe",
        "category": "artists",
        "user_count": 1,
        "total_scrobbles": 746,
        "shared_users": [
          "Rocky_stereo"
        ]
      },
      "Labels: Columbia": {
        "original_name": "Columbia",
        "category": "labels",
        "user_count": 2,
        "total_scrobbles": 637,
        "shared_users": [
          "EliasJ72",
          "Rocky_stereo"
        ]
      }
    },
    "type": "combined"
  }
}