{
  "artists": {
    "title": "Artistas (Por Usuarios Compartidos)",
    "data": {
      "Arca": 9224,
      "Radiohead": 4042,
      "The Beatles": 3516,
      "Taylor Swift": 3268,
      "The Smiths": 3191,
      "Pink Floyd": 3097,
      "Kanye West": 3032,
      "The Cure": 3016,
      "Talk Talk": 2895,
      "Björk": 2246,
      "Grimes": 2175,
      "Frank Ocean": 2113,
      "Charli xcx": 1962,
      "Tyler, The Creator": 1891,
      "Sigur Rós": 1856
    },
    "total": 47524,
    "details": {
      "Arca": {
        "user_count": 5,
        "total_scrobbles": 9224,
        "shared_users": [
          "GabredMared",
          "Nubis84",
          "alberto_gu",
          "Rocky_stereo",
          "paqueradejere"
        ],
        "user_plays": {
          "GabredMared": 8771,
          "Nubis84": 27,
          "Rocky_stereo": 2,
          "alberto_gu": 415,
          "paqueradejere": 9
        },
        "artist": "",
        "album": "",
        "track": ""
      },
      "Radiohead": {
        "user_count": 5,
        "total_scrobbles": 4042,
        "shared_users": [
          "GabredMared",
          "Nubis84",
          "alberto_gu",
          "Rocky_stereo",
          "paqueradejere"
        ],
        "user_plays": {
          "GabredMared": 1456,
          "Nubis84": 1397,
          "Rocky_stereo": 896,
          "alberto_gu": 286,
          "paqueradejere": 7
        },
        "artist": "",
        "album": "",
        "track": ""
      },
      "The Beatles": {
        "user_count": 5,
        "total_scrobbles": 3516,
        "shared_users": [
          "GabredMared",
          "Nubis84",
          "alberto_gu",
          "Rocky_stereo",
          "paqueradejere"
        ],
        "user_plays": {
          "GabredMared": 84,
          "Nubis84": 2025,
          "Rocky_stereo": 1148,
          "alberto_gu": 76,
          "paqueradejere": 183
        },
        "artist": "",
        "album": "",
        "track": ""
      },
      "Taylor Swift": {
        "user_count": 5,
        "total_scrobbles": 3268,
        "shared_users": [
          "GabredMared",
          "Nubis84",
          "alberto_gu",
          "Rocky_stereo",
          "paqueradejere"
        ],
        "user_plays": {
          "GabredMared": 3126,
          "Nubis84": 29,
          "Rocky_stereo": 58,
          "alberto_gu": 52,
          "paqueradejere": 3
        },
        "artist": "",
        "album": "",
        "track": ""
      },
      "The Smiths": {
        "user_count": 5,
        "total_scrobbles": 3191,
        "shared_users": [
          "GabredMared",
          "Nubis84",
          "alberto_gu",
          "Rocky_stereo",
          "paqueradejere"
        ],
        "user_plays": {
          "GabredMared": 633,
          "Nubis84": 162,
          "Rocky_stereo": 816,
          "alberto_gu": 1538,
          "paqueradejere": 42
        },
        "artist": "",
        "album": "",
        "track": ""
      },
      "Pink Floyd": {
        "user_count": 5,
        "total_scrobbles": 3097,
        "shared_users": [
          "GabredMared",
          "Nubis84",
          "alberto_gu",
          "Rocky_stereo",
          "paqueradejere"
        ],
        "user_plays": {
          "GabredMared": 271,
          "Nubis84": 965,
          "Rocky_stereo": 1536,
          "alberto_gu": 242,
          "paqueradejere": 83
        },
        "artist": "",
        "album": "",
        "track": ""
      },
      "Kanye West": {
        "user_count": 5,
        "total_scrobbles": 3032,
        "shared_users": [
          "GabredMared",
          "Nubis84",
          "alberto_gu",
          "Rocky_stereo",
          "paqueradejere"
        ],
        "user_plays": {
          "GabredMared": 507,
          "Nubis84": 186,
          "Rocky_stereo": 291,
          "alberto_gu": 2011,
          "paqueradejere": 37
        },
        "artist": "",
        "album": "",
        "track": ""
      },
      "The Cure": {
        "user_count": 5,
        "total_scrobbles": 3016,
        "shared_users": [
          "GabredMared",
          "Nubis84",
          "alberto_gu",
          "Rocky_stereo",
          "paqueradejere"
        ],
        "user_plays": {
          "GabredMared": 520,
          "Nubis84": 738,
          "Rocky_stereo": 1635,
          "alberto_gu": 40,
          "paqueradejere": 83
        },
        "artist": "",
        "album": "",
        "track": ""
      },
      "Talk Talk": {
        "user_count": 5,
        "total_scrobbles": 2895,
        "shared_users": [
          "GabredMared",
          "Nubis84",
          "alberto_gu",
          "Rocky_stereo",
          "paqueradejere"
        ],
        "user_plays": {
          "GabredMared": 2589,
          "Nubis84": 265,
          "Rocky_stereo": 2,
          "alberto_gu": 23,
          "paqueradejere": 16
        },
        "artist": "",
        "album": "",
        "track": ""
      },
      "Björk": {
        "user_count": 5,
        "total_scrobbles": 2246,
        "shared_users": [
          "GabredMared",
          "Nubis84",
          "alberto_gu",
          "Rocky_stereo",
          "paqueradejere"
        ],
        "user_plays": {
          "GabredMared": 1540,
          "Nubis84": 493,
          "Rocky_stereo": 85,
          "alberto_gu": 108,
          "paqueradejere": 20
        },
        "artist": "",
        "album": "",
        "track": ""
      },
      "Grimes": {
        "user_count": 5,
        "total_scrobbles": 2175,
        "shared_users": [
          "GabredMared",
          "Nubis84",
          "alberto_gu",
          "Rocky_stereo",
          "paqueradejere"
        ],
        "user_plays": {
          "GabredMared": 2042,
          "Nubis84": 73,
          "Rocky_stereo": 56,
          "alberto_gu": 1,
          "paqueradejere": 3
        },
        "artist": "",
        "album": "",
        "track": ""
      },
      "Frank Ocean": {
        "user_count": 5,
        "total_scrobbles": 2113,
        "shared_users": [
          "GabredMared",
          "Nubis84",
          "alberto_gu",
          "Rocky_stereo",
          "paqueradejere"
        ],
        "user_plays": {
          "GabredMared": 660,
          "Nubis84": 157,
          "Rocky_stereo": 89,
          "alberto_gu": 1197,
          "paqueradejere": 10
        },
        "artist": "",
        "album": "",
        "track": ""
      },
      "Charli xcx": {
        "user_count": 5,
        "total_scrobbles": 1962,
        "shared_users": [
          "GabredMared",
          "Nubis84",
          "alberto_gu",
          "Rocky_stereo",
          "paqueradejere"
        ],
        "user_plays": {
          "GabredMared": 1760,
          "Nubis84": 9,
          "Rocky_stereo": 19,
          "alberto_gu": 153,
          "paqueradejere": 21
        },
        "artist": "",
        "album": "",
        "track": ""
      },
      "Tyler, The Creator": {
        "user_count": 5,
        "total_scrobbles": 1891,
        "shared_users": [
          "GabredMared",
          "Nubis84",
          "alberto_gu",
          "Rocky_stereo",
          "paqueradejere"
        ],
        "user_plays": {
          "GabredMared": 241,
          "Nubis84": 17,
          "Rocky_stereo": 183,
          "alberto_gu": 1423,
          "paqueradejere": 27
        },
        "artist": "",
        "album": "",
        "track": ""
      },
      "Sigur Rós": {
        "user_count": 5,
        "total_scrobbles": 1856,
        "shared_users": [
          "GabredMared",
          "Nubis84",
          "alberto_gu",
          "Rocky_stereo",
          "paqueradejere"
        ],
        "user_plays": {
          "GabredMared": 761,
          "Nubis84": 987,
          "Rocky_stereo": 44,
          "alberto_gu": 13,
          "paqueradejere": 51
        },
        "artist": "",
        "album": "",
        "track": ""
      }
    },
    "type": "shared"
  },
  "albums": {
    "title": "Álbumes (Por Usuarios Compartidos)",
    "data": {
      "The Smiths - The Smiths": 1394,
      "Daft Punk - Discovery": 1034,
      "Kanye West - My Beautiful Dark Twisted Fantasy": 1034,
      "Radiohead - In Rainbows": 1014,
      "Madvillain - Madvillainy": 1005,
      "Frank Ocean - Blonde": 1001,
      "Cocteau Twins - Heaven or Las Vegas": 848,
      "Sigur Rós - Ágætis byrjun": 767,
      "Pink Floyd - The Dark Side of the Moon": 714,
      "The Smiths - The Queen Is Dead": 676,
      "Have a Nice Life - Deathconsciousness": 641,
      "Crystal Castles - Crystal Castles": 576,
      "Tyler, The Creator - IGOR": 568,
      "my bloody valentine - Loveless": 556,
      "Slowdive - Souvlaki": 494
    },
    "total": 12322,
    "details": {
      "The Smiths - The Smiths": {
        "user_count": 5,
        "total_scrobbles": 1394,
        "shared_users": [
          "GabredMared",
          "Nubis84",
          "alberto_gu",
          "Rocky_stereo",
          "paqueradejere"
        ],
        "user_plays": {
          "GabredMared": 471,
          "Nubis84": 2,
          "Rocky_stereo": 130,
          "alberto_gu": 771,
          "paqueradejere": 20
        },
        "artist": "The Smiths",
        "album": "The Smiths",
        "track": ""
      },
      "Daft Punk - Discovery": {
        "user_count": 5,
        "total_scrobbles": 1034,
        "shared_users": [
          "GabredMared",
          "Nubis84",
          "alberto_gu",
          "Rocky_stereo",
          "paqueradejere"
        ],
        "user_plays": {
          "GabredMared": 913,
          "Nubis84": 40,
          "Rocky_stereo": 6,
          "alberto_gu": 64,
          "paqueradejere": 11
        },
        "artist": "Daft Punk",
        "album": "Discovery",
        "track": ""
      },
      "Kanye West - My Beautiful Dark Twisted Fantasy": {
        "user_count": 5,
        "total_scrobbles": 1034,
        "shared_users": [
          "GabredMared",
          "Nubis84",
          "alberto_gu",
          "Rocky_stereo",
          "paqueradejere"
        ],
        "user_plays": {
          "GabredMared": 30,
          "Nubis84": 102,
          "Rocky_stereo": 49,
          "alberto_gu": 835,
          "paqueradejere": 18
        },
        "artist": "Kanye West",
        "album": "My Beautiful Dark Twisted Fantasy",
        "track": ""
      },
      "Radiohead - In Rainbows": {
        "user_count": 5,
        "total_scrobbles": 1014,
        "shared_users": [
          "GabredMared",
          "Nubis84",
          "alberto_gu",
          "Rocky_stereo",
          "paqueradejere"
        ],
        "user_plays": {
          "GabredMared": 349,
          "Nubis84": 181,
          "Rocky_stereo": 434,
          "alberto_gu": 49,
          "paqueradejere": 1
        },
        "artist": "Radiohead",
        "album": "In Rainbows",
        "track": ""
      },
      "Madvillain - Madvillainy": {
        "user_count": 5,
        "total_scrobbles": 1005,
        "shared_users": [
          "GabredMared",
          "Nubis84",
          "alberto_gu",
          "Rocky_stereo",
          "paqueradejere"
        ],
        "user_plays": {
          "GabredMared": 33,
          "Nubis84": 19,
          "Rocky_stereo": 70,
          "alberto_gu": 820,
          "paqueradejere": 63
        },
        "artist": "Madvillain",
        "album": "Madvillainy",
        "track": ""
      },
      "Frank Ocean - Blonde": {
        "user_count": 5,
        "total_scrobbles": 1001,
        "shared_users": [
          "GabredMared",
          "Nubis84",
          "alberto_gu",
          "Rocky_stereo",
          "paqueradejere"
        ],
        "user_plays": {
          "GabredMared": 429,
          "Nubis84": 35,
          "Rocky_stereo": 56,
          "alberto_gu": 471,
          "paqueradejere": 10
        },
        "artist": "Frank Ocean",
        "album": "Blonde",
        "track": ""
      },
      "Cocteau Twins - Heaven or Las Vegas": {
        "user_count": 5,
        "total_scrobbles": 848,
        "shared_users": [
          "GabredMared",
          "Nubis84",
          "alberto_gu",
          "Rocky_stereo",
          "paqueradejere"
        ],
        "user_plays": {
          "GabredMared": 608,
          "Nubis84": 48,
          "Rocky_stereo": 166,
          "alberto_gu": 1,
          "paqueradejere": 25
        },
        "artist": "Cocteau Twins",
        "album": "Heaven or Las Vegas",
        "track": ""
      },
      "Sigur Rós - Ágætis byrjun": {
        "user_count": 5,
        "total_scrobbles": 767,
        "shared_users": [
          "GabredMared",
          "Nubis84",
          "alberto_gu",
          "Rocky_stereo",
          "paqueradejere"
        ],
        "user_plays": {
          "GabredMared": 563,
          "Nubis84": 162,
          "Rocky_stereo": 19,
          "alberto_gu": 13,
          "paqueradejere": 10
        },
        "artist": "Sigur Rós",
        "album": "Ágætis byrjun",
        "track": ""
      },
      "Pink Floyd - The Dark Side of the Moon": {
        "user_count": 5,
        "total_scrobbles": 714,
        "shared_users": [
          "GabredMared",
          "Nubis84",
          "alberto_gu",
          "Rocky_stereo",
          "paqueradejere"
        ],
        "user_plays": {
          "GabredMared": 99,
          "Nubis84": 49,
          "Rocky_stereo": 498,
          "alberto_gu": 35,
          "paqueradejere": 33
        },
        "artist": "Pink Floyd",
        "album": "The Dark Side of the Moon",
        "track": ""
      },
      "The Smiths - The Queen Is Dead": {
        "user_count": 5,
        "total_scrobbles": 676,
        "shared_users": [
          "GabredMared",
          "Nubis84",
          "alberto_gu",
          "Rocky_stereo",
          "paqueradejere"
        ],
        "user_plays": {
          "GabredMared": 146,
          "Nubis84": 72,
          "Rocky_stereo": 152,
          "alberto_gu": 297,
          "paqueradejere": 9
        },
        "artist": "The Smiths",
        "album": "The Queen Is Dead",
        "track": ""
      },
      "Have a Nice Life - Deathconsciousness": {
        "user_count": 5,
        "total_scrobbles": 641,
        "shared_users": [
          "GabredMared",
          "Nubis84",
          "alberto_gu",
          "Rocky_stereo",
          "paqueradejere"
        ],
        "user_plays": {
          "GabredMared": 61,
          "Nubis84": 210,
          "Rocky_stereo": 291,
          "alberto_gu": 53,
          "paqueradejere": 26
        },
        "artist": "Have a Nice Life",
        "album": "Deathconsciousness",
        "track": ""
      },
      "Crystal Castles - Crystal Castles": {
        "user_count": 5,
        "total_scrobbles": 576,
        "shared_users": [
          "GabredMared",
          "Nubis84",
          "alberto_gu",
          "Rocky_stereo",
          "paqueradejere"
        ],
        "user_plays": {
          "GabredMared": 215,
          "Nubis84": 3,
          "Rocky_stereo": 61,
          "alberto_gu": 295,
          "paqueradejere": 2
        },
        "artist": "Crystal Castles",
        "album": "Crystal Castles",
        "track": ""
      },
      "Tyler, The Creator - IGOR": {
        "user_count": 5,
        "total_scrobbles": 568,
        "shared_users": [
          "GabredMared",
          "Nubis84",
          "alberto_gu",
          "Rocky_stereo",
          "paqueradejere"
        ],
        "user_plays": {
          "GabredMared": 61,
          "Nubis84": 12,
          "Rocky_stereo": 72,
          "alberto_gu": 411,
          "paqueradejere": 12
        },
        "artist": "Tyler, The Creator",
        "album": "IGOR",
        "track": ""
      },
      "my bloody valentine - Loveless": {
        "user_count": 5,
        "total_scrobbles": 556,
        "shared_users": [
          "GabredMared",
          "Nubis84",
          "alberto_gu",
          "Rocky_stereo",
          "paqueradejere"
        ],
        "user_plays": {
          "GabredMared": 20,
          "Nubis84": 66,
          "Rocky_stereo": 325,
          "alberto_gu": 89,
          "paqueradejere": 56
        },
        "artist": "my bloody valentine",
        "album": "Loveless",
        "track": ""
      },
      "Slowdive - Souvlaki": {
        "user_count": 5,
        "total_scrobbles": 494,
        "shared_users": [
          "GabredMared",
          "Nubis84",
          "alberto_gu",
          "Rocky_stereo",
          "paqueradejere"
        ],
        "user_plays": {
          "GabredMared": 28,
          "Nubis84": 94,
          "Rocky_stereo": 327,
          "alberto_gu": 37,
          "paqueradejere": 8
        },
        "artist": "Slowdive",
        "album": "Souvlaki",
        "track": ""
      }
    },
    "type": "shared"
  },
  "tracks": {
    "title": "Canciones (Por Usuarios Compartidos)",
    "data": {
      "Nirvana - Come as You Are": 205,
      "Sigur Rós - Svefn-g-englar": 193,
      "Frank Ocean - Pink + White": 188,
      "Madvillain - Accordion": 185,
      "Jeff Buckley - Corpus Christi Carol": 169,
      "Jeff Buckley - Grace": 138,
      "Massive Attack - Teardrop": 131,
      "Pink Floyd - The Great Gig in the Sky": 128,
      "LCD Soundsystem - Someone Great": 117,
      "my bloody valentine - When You Sleep": 110,
      "Have a Nice Life - Bloodhail": 100,
      "Daft Punk - Something About Us": 96,
      "Sigur Rós - Starálfur": 96,
      "Jeff Buckley - Last Goodbye": 95,
      "Mazzy Star - Fade Into You": 95
    },
    "total": 2046,
    "details": {
      "Nirvana - Come as You Are": {
        "user_count": 5,
        "total_scrobbles": 205,
        "shared_users": [
          "GabredMared",
          "Nubis84",
          "alberto_gu",
          "Rocky_stereo",
          "paqueradejere"
        ],
        "user_plays": {
          "GabredMared": 1,
          "Nubis84": 12,
          "Rocky_stereo": 9,
          "alberto_gu": 182,
          "paqueradejere": 1
        },
        "artist": "Nirvana",
        "album": "",
        "track": "Come as You Are"
      },
      "Sigur Rós - Svefn-g-englar": {
        "user_count": 5,
        "total_scrobbles": 193,
        "shared_users": [
          "GabredMared",
          "Nubis84",
          "alberto_gu",
          "Rocky_stereo",
          "paqueradejere"
        ],
        "user_plays": {
          "GabredMared": 148,
          "Nubis84": 38,
          "Rocky_stereo": 4,
          "alberto_gu": 2,
          "paqueradejere": 1
        },
        "artist": "Sigur Rós",
        "album": "",
        "track": "Svefn-g-englar"
      },
      "Frank Ocean - Pink + White": {
        "user_count": 5,
        "total_scrobbles": 188,
        "shared_users": [
          "GabredMared",
          "Nubis84",
          "alberto_gu",
          "Rocky_stereo",
          "paqueradejere"
        ],
        "user_plays": {
          "GabredMared": 36,
          "Nubis84": 3,
          "Rocky_stereo": 18,
          "alberto_gu": 130,
          "paqueradejere": 1
        },
        "artist": "Frank Ocean",
        "album": "",
        "track": "Pink + White"
      },
      "Madvillain - Accordion": {
        "user_count": 5,
        "total_scrobbles": 185,
        "shared_users": [
          "GabredMared",
          "Nubis84",
          "alberto_gu",
          "Rocky_stereo",
          "paqueradejere"
        ],
        "user_plays": {
          "GabredMared": 1,
          "Nubis84": 3,
          "Rocky_stereo": 4,
          "alberto_gu": 173,
          "paqueradejere": 4
        },
        "artist": "Madvillain",
        "album": "",
        "track": "Accordion"
      },
      "Jeff Buckley - Corpus Christi Carol": {
        "user_count": 5,
        "total_scrobbles": 169,
        "shared_users": [
          "GabredMared",
          "Nubis84",
          "alberto_gu",
          "Rocky_stereo",
          "paqueradejere"
        ],
        "user_plays": {
          "GabredMared": 155,
          "Nubis84": 2,
          "Rocky_stereo": 10,
          "alberto_gu": 1,
          "paqueradejere": 1
        },
        "artist": "Jeff Buckley",
        "album": "",
        "track": "Corpus Christi Carol"
      },
      "Jeff Buckley - Grace": {
        "user_count": 5,
        "total_scrobbles": 138,
        "shared_users": [
          "GabredMared",
          "Nubis84",
          "alberto_gu",
          "Rocky_stereo",
          "paqueradejere"
        ],
        "user_plays": {
          "GabredMared": 73,
          "Nubis84": 17,
          "Rocky_stereo": 20,
          "alberto_gu": 25,
          "paqueradejere": 3
        },
        "artist": "Jeff Buckley",
        "album": "",
        "track": "Grace"
      },
      "Massive Attack - Teardrop": {
        "user_count": 5,
        "total_scrobbles": 131,
        "shared_users": [
          "GabredMared",
          "Nubis84",
          "alberto_gu",
          "Rocky_stereo",
          "paqueradejere"
        ],
        "user_plays": {
          "GabredMared": 92,
          "Nubis84": 26,
          "Rocky_stereo": 3,
          "alberto_gu": 7,
          "paqueradejere": 3
        },
        "artist": "Massive Attack",
        "album": "",
        "track": "Teardrop"
      },
      "Pink Floyd - The Great Gig in the Sky": {
        "user_count": 5,
        "total_scrobbles": 128,
        "shared_users": [
          "GabredMared",
          "Nubis84",
          "alberto_gu",
          "Rocky_stereo",
          "paqueradejere"
        ],
        "user_plays": {
          "GabredMared": 38,
          "Nubis84": 17,
          "Rocky_stereo": 68,
          "alberto_gu": 2,
          "paqueradejere": 3
        },
        "artist": "Pink Floyd",
        "album": "",
        "track": "The Great Gig in the Sky"
      },
      "LCD Soundsystem - Someone Great": {
        "user_count": 5,
        "total_scrobbles": 117,
        "shared_users": [
          "GabredMared",
          "Nubis84",
          "alberto_gu",
          "Rocky_stereo",
          "paqueradejere"
        ],
        "user_plays": {
          "GabredMared": 22,
          "Nubis84": 21,
          "Rocky_stereo": 1,
          "alberto_gu": 71,
          "paqueradejere": 2
        },
        "artist": "LCD Soundsystem",
        "album": "",
        "track": "Someone Great"
      },
      "my bloody valentine - When You Sleep": {
        "user_count": 5,
        "total_scrobbles": 110,
        "shared_users": [
          "GabredMared",
          "Nubis84",
          "alberto_gu",
          "Rocky_stereo",
          "paqueradejere"
        ],
        "user_plays": {
          "GabredMared": 2,
          "Nubis84": 20,
          "Rocky_stereo": 66,
          "alberto_gu": 17,
          "paqueradejere": 5
        },
        "artist": "my bloody valentine",
        "album": "",
        "track": "When You Sleep"
      },
      "Have a Nice Life - Bloodhail": {
        "user_count": 5,
        "total_scrobbles": 100,
        "shared_users": [
          "GabredMared",
          "Nubis84",
          "alberto_gu",
          "Rocky_stereo",
          "paqueradejere"
        ],
        "user_plays": {
          "GabredMared": 3,
          "Nubis84": 49,
          "Rocky_stereo": 33,
          "alberto_gu": 10,
          "paqueradejere": 5
        },
        "artist": "Have a Nice Life",
        "album": "",
        "track": "Bloodhail"
      },
      "Daft Punk - Something About Us": {
        "user_count": 5,
        "total_scrobbles": 96,
        "shared_users": [
          "GabredMared",
          "Nubis84",
          "alberto_gu",
          "Rocky_stereo",
          "paqueradejere"
        ],
        "user_plays": {
          "GabredMared": 80,
          "Nubis84": 7,
          "Rocky_stereo": 6,
          "alberto_gu": 2,
          "paqueradejere": 1
        },
        "artist": "Daft Punk",
        "album": "",
        "track": "Something About Us"
      },
      "Sigur Rós - Starálfur": {
        "user_count": 5,
        "total_scrobbles": 96,
        "shared_users": [
          "GabredMared",
          "Nubis84",
          "alberto_gu",
          "Rocky_stereo",
          "paqueradejere"
        ],
        "user_plays": {
          "GabredMared": 61,
          "Nubis84": 30,
          "Rocky_stereo": 2,
          "alberto_gu": 2,
          "paqueradejere": 1
        },
        "artist": "Sigur Rós",
        "album": "",
        "track": "Starálfur"
      },
      "Jeff Buckley - Last Goodbye": {
        "user_count": 5,
        "total_scrobbles": 95,
        "shared_users": [
          "GabredMared",
          "Nubis84",
          "alberto_gu",
          "Rocky_stereo",
          "paqueradejere"
        ],
        "user_plays": {
          "GabredMared": 45,
          "Nubis84": 25,
          "Rocky_stereo": 16,
          "alberto_gu": 8,
          "paqueradejere": 1
        },
        "artist": "Jeff Buckley",
        "album": "",
        "track": "Last Goodbye"
      },
      "Mazzy Star - Fade Into You": {
        "user_count": 5,
        "total_scrobbles": 95,
        "shared_users": [
          "GabredMared",
          "Nubis84",
          "alberto_gu",
          "Rocky_stereo",
          "paqueradejere"
        ],
        "user_plays": {
          "GabredMared": 1,
          "Nubis84": 61,
          "Rocky_stereo": 26,
          "alberto_gu": 5,
          "paqueradejere": 2
        },
        "artist": "Mazzy Star",
        "album": "",
        "track": "Fade Into You"
      }
    },
    "type": "shared"
  },
  "genres": {
    "title": "Géneros (Por Usuarios Compartidos)",
    "data": {
      "pop": 23009,
      "electronic": 17012,
      "Hip-Hop": 14010,
      "female vocalists": 13807,
      "indie": 13533,
      "rap": 11349,
      "rock": 11282,
      "latin": 10146,
      "indie pop": 9947,
      "folk": 9207,
      "Progressive rock": 7934,
      "ambient": 7345,
      "singer-songwriter": 6797,
      "experimental": 6379,
      "post-rock": 5995
    },
    "total": 167752,
    "details": {
      "pop": {
        "user_count": 5,
        "total_scrobbles": 23009,
        "shared_users": [
          "GabredMared",
          "alberto_gu",
          "Nubis84",
          "Rocky_stereo",
          "paqueradejere"
        ],
        "user_plays": {
          "Nubis84": 2131,
          "alberto_gu": 3073,
          "Rocky_stereo": 676,
          "paqueradejere": 289,
          "GabredMared": 16840
        },
        "artist": "",
        "album": "",
        "track": ""
      },
      "electronic": {
        "user_count": 5,
        "total_scrobbles": 17012,
        "shared_users": [
          "GabredMared",
          "Nubis84",
          "alberto_gu",
          "Rocky_stereo",
          "paqueradejere"
        ],
        "user_plays": {
          "Nubis84": 2952,
          "paqueradejere": 3888,
          "GabredMared": 6865,
          "Rocky_stereo": 547,
          "alberto_gu": 2760
        },
        "artist": "",
        "album": "",
        "track": ""
      },
      "Hip-Hop": {
        "user_count": 5,
        "total_scrobbles": 14010,
        "shared_users": [
          "GabredMared",
          "Nubis84",
          "alberto_gu",
          "Rocky_stereo",
          "paqueradejere"
        ],
        "user_plays": {
          "Nubis84": 830,
          "paqueradejere": 618,
          "GabredMared": 4267,
          "Rocky_stereo": 1291,
          "alberto_gu": 7004
        },
        "artist": "",
        "album": "",
        "track": ""
      },
      "female vocalists": {
        "user_count": 5,
        "total_scrobbles": 13807,
        "shared_users": [
          "GabredMared",
          "alberto_gu",
          "Nubis84",
          "Rocky_stereo",
          "paqueradejere"
        ],
        "user_plays": {
          "Nubis84": 1797,
          "alberto_gu": 1343,
          "paqueradejere": 340,
          "GabredMared": 9765,
          "Rocky_stereo": 562
        },
        "artist": "",
        "album": "",
        "track": ""
      },
      "indie": {
        "user_count": 5,
        "total_scrobbles": 13533,
        "shared_users": [
          "GabredMared",
          "alberto_gu",
          "Nubis84",
          "Rocky_stereo",
          "paqueradejere"
        ],
        "user_plays": {
          "Nubis84": 2200,
          "alberto_gu": 1783,
          "GabredMared": 6858,
          "Rocky_stereo": 1783,
          "paqueradejere": 909
        },
        "artist": "",
        "album": "",
        "track": ""
      },
      "rap": {
        "user_count": 5,
        "total_scrobbles": 11349,
        "shared_users": [
          "GabredMared",
          "Nubis84",
          "alberto_gu",
          "Rocky_stereo",
          "paqueradejere"
        ],
        "user_plays": {
          "Rocky_stereo": 1673,
          "Nubis84": 754,
          "paqueradejere": 447,
          "GabredMared": 2172,
          "alberto_gu": 6303
        },
        "artist": "",
        "album": "",
        "track": ""
      },
      "rock": {
        "user_count": 5,
        "total_scrobbles": 11282,
        "shared_users": [
          "GabredMared",
          "alberto_gu",
          "Nubis84",
          "Rocky_stereo",
          "paqueradejere"
        ],
        "user_plays": {
          "Rocky_stereo": 2389,
          "Nubis84": 3691,
          "alberto_gu": 1568,
          "paqueradejere": 399,
          "GabredMared": 3235
        },
        "artist": "",
        "album": "",
        "track": ""
      },
      "latin": {
        "user_count": 5,
        "total_scrobbles": 10146,
        "shared_users": [
          "GabredMared",
          "alberto_gu",
          "Nubis84",
          "Rocky_stereo",
          "paqueradejere"
        ],
        "user_plays": {
          "Rocky_stereo": 3097,
          "alberto_gu": 2301,
          "Nubis84": 299,
          "GabredMared": 4375,
          "paqueradejere": 74
        },
        "artist": "",
        "album": "",
        "track": ""
      },
      "indie pop": {
        "user_count": 5,
        "total_scrobbles": 9947,
        "shared_users": [
          "GabredMared",
          "alberto_gu",
          "Nubis84",
          "Rocky_stereo",
          "paqueradejere"
        ],
        "user_plays": {
          "alberto_gu": 610,
          "Rocky_stereo": 842,
          "Nubis84": 466,
          "GabredMared": 7592,
          "paqueradejere": 437
        },
        "artist": "",
        "album": "",
        "track": ""
      },
      "folk": {
        "user_count": 5,
        "total_scrobbles": 9207,
        "shared_users": [
          "GabredMared",
          "Nubis84",
          "alberto_gu",
          "Rocky_stereo",
          "paqueradejere"
        ],
        "user_plays": {
          "Nubis84": 2151,
          "Rocky_stereo": 541,
          "paqueradejere": 475,
          "GabredMared": 5223,
          "alberto_gu": 817
        },
        "artist": "",
        "album": "",
        "track": ""
      },
      "Progressive rock": {
        "user_count": 5,
        "total_scrobbles": 7934,
        "shared_users": [
          "GabredMared",
          "Nubis84",
          "alberto_gu",
          "Rocky_stereo",
          "paqueradejere"
        ],
        "user_plays": {
          "Nubis84": 2488,
          "paqueradejere": 100,
          "GabredMared": 3794,
          "Rocky_stereo": 1281,
          "alberto_gu": 271
        },
        "artist": "",
        "album": "",
        "track": ""
      },
      "ambient": {
        "user_count": 5,
        "total_scrobbles": 7345,
        "shared_users": [
          "GabredMared",
          "Nubis84",
          "alberto_gu",
          "Rocky_stereo",
          "paqueradejere"
        ],
        "user_plays": {
          "GabredMared": 457,
          "Nubis84": 4144,
          "paqueradejere": 2217,
          "alberto_gu": 273,
          "Rocky_stereo": 254
        },
        "artist": "",
        "album": "",
        "track": ""
      },
      "singer-songwriter": {
        "user_count": 5,
        "total_scrobbles": 6797,
        "shared_users": [
          "GabredMared",
          "alberto_gu",
          "Nubis84",
          "Rocky_stereo",
          "paqueradejere"
        ],
        "user_plays": {
          "Nubis84": 2719,
          "Rocky_stereo": 390,
          "alberto_gu": 752,
          "paqueradejere": 453,
          "GabredMared": 2483
        },
        "artist": "",
        "album": "",
        "track": ""
      },
      "experimental": {
        "user_count": 5,
        "total_scrobbles": 6379,
        "shared_users": [
          "GabredMared",
          "alberto_gu",
          "Nubis84",
          "Rocky_stereo",
          "paqueradejere"
        ],
        "user_plays": {
          "Nubis84": 1781,
          "alberto_gu": 361,
          "GabredMared": 1664,
          "paqueradejere": 1579,
          "Rocky_stereo": 994
        },
        "artist": "",
        "album": "",
        "track": ""
      },
      "post-rock": {
        "user_count": 5,
        "total_scrobbles": 5995,
        "shared_users": [
          "GabredMared",
          "alberto_gu",
          "Nubis84",
          "Rocky_stereo",
          "paqueradejere"
        ],
        "user_plays": {
          "Nubis84": 3040,
          "Rocky_stereo": 635,
          "alberto_gu": 115,
          "paqueradejere": 1013,
          "GabredMared": 1192
        },
        "artist": "",
        "album": "",
        "track": ""
      }
    },
    "type": "shared"
  },
  "labels": {
    "title": "Sellos (Por Usuarios Compartidos)",
    "data": {
      "Columbia": 3345,
      "XL Recordings": 3238,
      "Interscope Records": 2839,
      "4AD": 2205,
      "EMI": 2059,
      "Atlantic": 1857,
      "Capitol Records": 1805,
      "Warner Bros. Records": 1686,
      "Sony Music": 1511,
      "[no label]": 1421,
      "Polydor": 1245,
      "Republic Records": 1113,
      "Parlophone": 1070,
      "RCA": 1057,
      "Boys Don’t Cry": 1001
    },
    "total": 27452,
    "details": {
      "Columbia": {
        "user_count": 5,
        "total_scrobbles": 3345,
        "shared_users": [
          "GabredMared",
          "Nubis84",
          "alberto_gu",
          "Rocky_stereo",
          "paqueradejere"
        ],
        "user_plays": {
          "GabredMared": 1704,
          "Nubis84": 567,
          "Rocky_stereo": 580,
          "alberto_gu": 316,
          "paqueradejere": 178
        },
        "artist": "",
        "album": "",
        "track": ""
      },
      "XL Recordings": {
        "user_count": 5,
        "total_scrobbles": 3238,
        "shared_users": [
          "GabredMared",
          "Nubis84",
          "alberto_gu",
          "Rocky_stereo",
          "paqueradejere"
        ],
        "user_plays": {
          "GabredMared": 2852,
          "Nubis84": 145,
          "Rocky_stereo": 51,
          "alberto_gu": 167,
          "paqueradejere": 23
        },
        "artist": "",
        "album": "",
        "track": ""
      },
      "Interscope Records": {
        "user_count": 5,
        "total_scrobbles": 2839,
        "shared_users": [
          "GabredMared",
          "Nubis84",
          "alberto_gu",
          "Rocky_stereo",
          "paqueradejere"
        ],
        "user_plays": {
          "GabredMared": 2471,
          "Nubis84": 148,
          "Rocky_stereo": 48,
          "alberto_gu": 142,
          "paqueradejere": 30
        },
        "artist": "",
        "album": "",
        "track": ""
      },
      "4AD": {
        "user_count": 5,
        "total_scrobbles": 2205,
        "shared_users": [
          "GabredMared",
          "Nubis84",
          "alberto_gu",
          "Rocky_stereo",
          "paqueradejere"
        ],
        "user_plays": {
          "GabredMared": 1905,
          "Nubis84": 192,
          "Rocky_stereo": 76,
          "alberto_gu": 6,
          "paqueradejere": 26
        },
        "artist": "",
        "album": "",
        "track": ""
      },
      "EMI": {
        "user_count": 5,
        "total_scrobbles": 2059,
        "shared_users": [
          "GabredMared",
          "Nubis84",
          "alberto_gu",
          "Rocky_stereo",
          "paqueradejere"
        ],
        "user_plays": {
          "GabredMared": 1182,
          "Nubis84": 249,
          "Rocky_stereo": 374,
          "alberto_gu": 244,
          "paqueradejere": 10
        },
        "artist": "",
        "album": "",
        "track": ""
      },
      "Atlantic": {
        "user_count": 5,
        "total_scrobbles": 1857,
        "shared_users": [
          "GabredMared",
          "Nubis84",
          "alberto_gu",
          "Rocky_stereo",
          "paqueradejere"
        ],
        "user_plays": {
          "GabredMared": 1254,
          "Nubis84": 318,
          "Rocky_stereo": 53,
          "alberto_gu": 197,
          "paqueradejere": 35
        },
        "artist": "",
        "album": "",
        "track": ""
      },
      "Capitol Records": {
        "user_count": 5,
        "total_scrobbles": 1805,
        "shared_users": [
          "GabredMared",
          "Nubis84",
          "alberto_gu",
          "Rocky_stereo",
          "paqueradejere"
        ],
        "user_plays": {
          "GabredMared": 1424,
          "Nubis84": 185,
          "Rocky_stereo": 69,
          "alberto_gu": 76,
          "paqueradejere": 51
        },
        "artist": "",
        "album": "",
        "track": ""
      },
      "Warner Bros. Records": {
        "user_count": 5,
        "total_scrobbles": 1686,
        "shared_users": [
          "GabredMared",
          "Nubis84",
          "alberto_gu",
          "Rocky_stereo",
          "paqueradejere"
        ],
        "user_plays": {
          "GabredMared": 701,
          "Nubis84": 498,
          "Rocky_stereo": 58,
          "alberto_gu": 309,
          "paqueradejere": 120
        },
        "artist": "",
        "album": "",
        "track": ""
      },
      "Sony Music": {
        "user_count": 5,
        "total_scrobbles": 1511,
        "shared_users": [
          "GabredMared",
          "Nubis84",
          "alberto_gu",
          "Rocky_stereo",
          "paqueradejere"
        ],
        "user_plays": {
          "GabredMared": 1154,
          "Nubis84": 119,
          "Rocky_stereo": 139,
          "alberto_gu": 52,
          "paqueradejere": 47
        },
        "artist": "",
        "album": "",
        "track": ""
      },
      "[no label]": {
        "user_count": 5,
        "total_scrobbles": 1421,
        "shared_users": [
          "GabredMared",
          "Nubis84",
          "alberto_gu",
          "Rocky_stereo",
          "paqueradejere"
        ],
        "user_plays": {
          "GabredMared": 615,
          "Nubis84": 399,
          "Rocky_stereo": 223,
          "alberto_gu": 22,
          "paqueradejere": 162
        },
        "artist": "",
        "album": "",
        "track": ""
      },
      "Polydor": {
        "user_count": 5,
        "total_scrobbles": 1245,
        "shared_users": [
          "GabredMared",
          "Nubis84",
          "alberto_gu",
          "Rocky_stereo",
          "paqueradejere"
        ],
        "user_plays": {
          "GabredMared": 780,
          "Nubis84": 153,
          "Rocky_stereo": 190,
          "alberto_gu": 95,
          "paqueradejere": 27
        },
        "artist": "",
        "album": "",
        "track": ""
      },
      "Republic Records": {
        "user_count": 5,
        "total_scrobbles": 1113,
        "shared_users": [
          "GabredMared",
          "Nubis84",
          "alberto_gu",
          "Rocky_stereo",
          "paqueradejere"
        ],
        "user_plays": {
          "GabredMared": 1036,
          "Nubis84": 27,
          "Rocky_stereo": 8,
          "alberto_gu": 25,
          "paqueradejere": 17
        },
        "artist": "",
        "album": "",
        "track": ""
      },
      "Parlophone": {
        "user_count": 5,
        "total_scrobbles": 1070,
        "shared_users": [
          "GabredMared",
          "Nubis84",
          "alberto_gu",
          "Rocky_stereo",
          "paqueradejere"
        ],
        "user_plays": {
          "GabredMared": 121,
          "Nubis84": 540,
          "Rocky_stereo": 288,
          "alberto_gu": 72,
          "paqueradejere": 49
        },
        "artist": "",
        "album": "",
        "track": ""
      },
      "RCA": {
        "user_count": 5,
        "total_scrobbles": 1057,
        "shared_users": [
          "GabredMared",
          "Nubis84",
          "alberto_gu",
          "Rocky_stereo",
          "paqueradejere"
        ],
        "user_plays": {
          "GabredMared": 652,
          "Nubis84": 81,
          "Rocky_stereo": 170,
          "alberto_gu": 141,
          "paqueradejere": 13
        },
        "artist": "",
        "album": "",
        "track": ""
      },
      "Boys Don’t Cry": {
        "user_count": 5,
        "total_scrobbles": 1001,
        "shared_users": [
          "GabredMared",
          "Nubis84",
          "alberto_gu",
          "Rocky_stereo",
          "paqueradejere"
        ],
        "user_plays": {
          "GabredMared": 429,
          "Nubis84": 35,
          "Rocky_stereo": 56,
          "alberto_gu": 471,
          "paqueradejere": 10
        },
        "artist": "",
        "album": "",
        "track": ""
      }
    },
    "type": "shared"
  },
  "release_years": {
    "title": "Años de Lanzamiento (Por Usuarios Compartidos)",
    "data": {
      "2017": 7118,
      "2015": 5267,
      "2018": 5184,
      "2021": 5065,
      "2016": 4513,
      "2020": 3670,
      "2014": 3634,
      "2022": 3572,
      "1978": 3283,
      "2024": 3247,
      "2013": 2982,
      "2019": 2943,
      "2023": 2912,
      "2006": 2880,
      "2008": 2812
    },
    "total": 59082,
    "details": {
      "2017": {
        "user_count": 5,
        "total_scrobbles": 7118,
        "shared_users": [
          "GabredMared",
          "Nubis84",
          "alberto_gu",
          "Rocky_stereo",
          "paqueradejere"
        ],
        "user_plays": {
          "GabredMared": 2873,
          "Nubis84": 994,
          "Rocky_stereo": 886,
          "alberto_gu": 1772,
          "paqueradejere": 593
        },
        "artist": "",
        "album": "",
        "track": ""
      },
      "2015": {
        "user_count": 5,
        "total_scrobbles": 5267,
        "shared_users": [
          "GabredMared",
          "Nubis84",
          "alberto_gu",
          "Rocky_stereo",
          "paqueradejere"
        ],
        "user_plays": {
          "GabredMared": 3291,
          "Nubis84": 927,
          "Rocky_stereo": 491,
          "alberto_gu": 233,
          "paqueradejere": 325
        },
        "artist": "",
        "album": "",
        "track": ""
      },
      "2018": {
        "user_count": 5,
        "total_scrobbles": 5184,
        "shared_users": [
          "GabredMared",
          "Nubis84",
          "alberto_gu",
          "Rocky_stereo",
          "paqueradejere"
        ],
        "user_plays": {
          "GabredMared": 2119,
          "Nubis84": 826,
          "Rocky_stereo": 609,
          "alberto_gu": 1006,
          "paqueradejere": 624
        },
        "artist": "",
        "album": "",
        "track": ""
      },
      "2021": {
        "user_count": 5,
        "total_scrobbles": 5065,
        "shared_users": [
          "GabredMared",
          "Nubis84",
          "alberto_gu",
          "Rocky_stereo",
          "paqueradejere"
        ],
        "user_plays": {
          "GabredMared": 3543,
          "Nubis84": 415,
          "Rocky_stereo": 208,
          "alberto_gu": 390,
          "paqueradejere": 509
        },
        "artist": "",
        "album": "",
        "track": ""
      },
      "2016": {
        "user_count": 5,
        "total_scrobbles": 4513,
        "shared_users": [
          "GabredMared",
          "Nubis84",
          "alberto_gu",
          "Rocky_stereo",
          "paqueradejere"
        ],
        "user_plays": {
          "GabredMared": 1368,
          "Nubis84": 932,
          "Rocky_stereo": 841,
          "alberto_gu": 964,
          "paqueradejere": 408
        },
        "artist": "",
        "album": "",
        "track": ""
      },
      "2020": {
        "user_count": 5,
        "total_scrobbles": 3670,
        "shared_users": [
          "GabredMared",
          "Nubis84",
          "alberto_gu",
          "Rocky_stereo",
          "paqueradejere"
        ],
        "user_plays": {
          "GabredMared": 2346,
          "Nubis84": 314,
          "Rocky_stereo": 371,
          "alberto_gu": 197,
          "paqueradejere": 442
        },
        "artist": "",
        "album": "",
        "track": ""
      },
      "2014": {
        "user_count": 5,
        "total_scrobbles": 3634,
        "shared_users": [
          "GabredMared",
          "Nubis84",
          "alberto_gu",
          "Rocky_stereo",
          "paqueradejere"
        ],
        "user_plays": {
          "GabredMared": 1272,
          "Nubis84": 871,
          "Rocky_stereo": 443,
          "alberto_gu": 806,
          "paqueradejere": 242
        },
        "artist": "",
        "album": "",
        "track": ""
      },
      "2022": {
        "user_count": 5,
        "total_scrobbles": 3572,
        "shared_users": [
          "GabredMared",
          "Nubis84",
          "alberto_gu",
          "Rocky_stereo",
          "paqueradejere"
        ],
        "user_plays": {
          "GabredMared": 2200,
          "Nubis84": 434,
          "Rocky_stereo": 474,
          "alberto_gu": 145,
          "paqueradejere": 319
        },
        "artist": "",
        "album": "",
        "track": ""
      },
      "1978": {
        "user_count": 5,
        "total_scrobbles": 3283,
        "shared_users": [
          "GabredMared",
          "Nubis84",
          "alberto_gu",
          "Rocky_stereo",
          "paqueradejere"
        ],
        "user_plays": {
          "GabredMared": 2801,
          "Nubis84": 57,
          "Rocky_stereo": 268,
          "alberto_gu": 118,
          "paqueradejere": 39
        },
        "artist": "",
        "album": "",
        "track": ""
      },
      "2024": {
        "user_count": 5,
        "total_scrobbles": 3247,
        "shared_users": [
          "GabredMared",
          "Nubis84",
          "alberto_gu",
          "Rocky_stereo",
          "paqueradejere"
        ],
        "user_plays": {
          "GabredMared": 1958,
          "Nubis84": 189,
          "Rocky_stereo": 251,
          "alberto_gu": 279,
          "paqueradejere": 570
        },
        "artist": "",
        "album": "",
        "track": ""
      },
      "2013": {
        "user_count": 5,
        "total_scrobbles": 2982,
        "shared_users": [
          "GabredMared",
          "Nubis84",
          "alberto_gu",
          "Rocky_stereo",
          "paqueradejere"
        ],
        "user_plays": {
          "GabredMared": 1163,
          "Nubis84": 731,
          "Rocky_stereo": 597,
          "alberto_gu": 318,
          "paqueradejere": 173
        },
        "artist": "",
        "album": "",
        "track": ""
      },
      "2019": {
        "user_count": 5,
        "total_scrobbles": 2943,
        "shared_users": [
          "GabredMared",
          "Nubis84",
          "alberto_gu",
          "Rocky_stereo",
          "paqueradejere"
        ],
        "user_plays": {
          "GabredMared": 910,
          "Nubis84": 535,
          "Rocky_stereo": 444,
          "alberto_gu": 415,
          "paqueradejere": 639
        },
        "artist": "",
        "album": "",
        "track": ""
      },
      "2023": {
        "user_count": 5,
        "total_scrobbles": 2912,
        "shared_users": [
          "GabredMared",
          "Nubis84",
          "alberto_gu",
          "Rocky_stereo",
          "paqueradejere"
        ],
        "user_plays": {
          "GabredMared": 1442,
          "Nubis84": 203,
          "Rocky_stereo": 353,
          "alberto_gu": 291,
          "paqueradejere": 623
        },
        "artist": "",
        "album": "",
        "track": ""
      },
      "2006": {
        "user_count": 5,
        "total_scrobbles": 2880,
        "shared_users": [
          "GabredMared",
          "Nubis84",
          "alberto_gu",
          "Rocky_stereo",
          "paqueradejere"
        ],
        "user_plays": {
          "GabredMared": 632,
          "Nubis84": 1008,
          "Rocky_stereo": 184,
          "alberto_gu": 916,
          "paqueradejere": 140
        },
        "artist": "",
        "album": "",
        "track": ""
      },
      "2008": {
        "user_count": 5,
        "total_scrobbles": 2812,
        "shared_users": [
          "GabredMared",
          "Nubis84",
          "alberto_gu",
          "Rocky_stereo",
          "paqueradejere"
        ],
        "user_plays": {
          "GabredMared": 396,
          "Nubis84": 840,
          "Rocky_stereo": 555,
          "alberto_gu": 763,
          "paqueradejere": 258
        },
        "artist": "",
        "album": "",
        "track": ""
      }
    },
    "type": "shared"
  }
}